pygeoda/gda.py
pygeoda/_libgeoda.cpython-312-i386-linux-musl.so
pygeoda/libgeoda.py
pygeoda/__init__.py
pygeoda/clustering/azp.py
pygeoda/clustering/skater.py
pygeoda/clustering/maxp.py
pygeoda/clustering/schc.py
pygeoda/clustering/__init__.py
pygeoda/clustering/utils.py
pygeoda/clustering/validation.py
pygeoda/clustering/redcap.py
pygeoda/data/transform.py
pygeoda/data/__init__.py
pygeoda/sa/quantile_lisa.py
pygeoda/sa/neighbor_match_test.py
pygeoda/sa/geary.py
pygeoda/sa/getisord.py
pygeoda/sa/joincount.py
pygeoda/sa/lisa.py
pygeoda/sa/moran.py
pygeoda/sa/__init__.py
pygeoda/classify/breaks.py
pygeoda/classify/__init__.py
pygeoda/weights/weight.py
pygeoda/weights/distance.py
pygeoda/weights/queen.py
pygeoda/weights/kernel.py
pygeoda/weights/rook.py
pygeoda/weights/__init__.py
pygeoda-0.1.2.dist-info/LICENSE
pygeoda-0.1.2.dist-info/WHEEL
pygeoda-0.1.2.dist-info/RECORD
pygeoda-0.1.2.dist-info/top_level.txt
pygeoda-0.1.2.dist-info/METADATA
pygeoda.libs/libstdc++-0530927c.so.6.0.32
pygeoda.libs/libgcc_s-1257a076.so.1
